acex_mcp/__init__.py
acex_mcp/__main__.py
acex_mcp/server.py
acex_mcp_server-0.2.5.dist-info/METADATA
acex_mcp_server-0.2.5.dist-info/WHEEL
acex_mcp_server-0.2.5.dist-info/entry_points.txt
acex_mcp_server-0.2.5.dist-info/RECORD
