Metadata-Version: 2.4
Name: acex-mcp-server
Version: 0.2.5
Summary: ACE-X MCP Server - Model Context Protocol server for ACE-X
License: AGPL-3.0
Author: Johan Lahti
Author-email: johan.lahti@acebit.se
Requires-Python: >=3.13,<4.0
Classifier: License :: OSI Approved :: GNU Affero General Public License v3
Classifier: Programming Language :: Python :: 3
Classifier: Programming Language :: Python :: 3.13
Classifier: Programming Language :: Python :: 3.14
Requires-Dist: fastmcp (>=2.13.0.2,<3.0.0.0)
Requires-Dist: mcp (>=1.1.0,<2.0.0)
Requires-Dist: requests (>=2.32.0,<3.0.0)
